CONTRIBUTING.md
LICENSE.txt
MANIFEST.in
README.md
setup.cfg
setup.py
tests/__init__.py
tests/api_tests.py
tests/auth_tests.py
uberpy/__init__.py
uberpy/api.py
uberpy/errors.py
uberpy/uber.py
uberpy.egg-info/PKG-INFO
uberpy.egg-info/SOURCES.txt
uberpy.egg-info/dependency_links.txt
uberpy.egg-info/top_level.txt