Metadata-Version: 1.0
Name: uberpy
Version: 1.0
Summary: A pure python wrapper for the Uber API.
Home-page: https://github.com/vivangkumar/uberpy
Author: Vivan Kumar
Author-email: vivangkumar@gmail.com
License: MIT
Keywords: uber api wrapper library
Platform: UNKNOWN
Classifier: Development Status :: 5 - Production/Stable
Classifier: Intended Audience :: Developers
Classifier: Topic :: Software Development :: Libraries :: Python Modules
Classifier: License :: OSI Approved :: MIT License
